drsclient/__init__.py
drsclient/client.py
drsclient-0.4.0.dist-info/METADATA
drsclient-0.4.0.dist-info/WHEEL
drsclient-0.4.0.dist-info/licenses/LICENSE
drsclient-0.4.0.dist-info/licenses/NOTICE
drsclient-0.4.0.dist-info/RECORD
