Metadata-Version: 2.4
Name: drsclient
Version: 0.4.0
Summary: GA4GH DRS Client
License: Apache-2.0
License-File: LICENSE
License-File: NOTICE
Author: CTDS UChicago
Author-email: cdis@uchicago.edu
Requires-Python: >=3.13,<4
Classifier: License :: OSI Approved :: Apache Software License
Classifier: Programming Language :: Python :: 3
Classifier: Programming Language :: Python :: 3.13
Classifier: Programming Language :: Python :: 3.14
Requires-Dist: httpx (>=0.28.1,<1.0.0)
Requires-Dist: requests (>=2.23.0,<3.0.0)
